exer7/Estrutural/counterbin_struct.v

// MÓDULO 1: O FLIP-FLOP D

module ffd (
    input wire clk,
    input wire rst,
    input wire d,
    output reg q   
);

    always @(posedge clk or posedge rst) begin
        if (rst)
            q <= 1'b0;
        else
            q <= d;
    end
endmodule

// MÓDULO 2: O CONTADOR ESTRUTURAL

module counterbin_struct (
    input wire clk,
    input wire rst,
    output wire [3:0] q
);

    wire [3:0] d;          
    wire [3:0] q_interno; 

    assign d = q_interno + 1;
    
    ffd U0_ffd ( .clk(clk), .rst(rst), .d(d[0]), .q(q_interno[0]) );
    ffd U1_ffd ( .clk(clk), .rst(rst), .d(d[1]), .q(q_interno[1]) );
    ffd U2_ffd ( .clk(clk), .rst(rst), .d(d[2]), .q(q_interno[2]) );
    ffd U3_ffd ( .clk(clk), .rst(rst), .d(d[3]), .q(q_interno[3]) );

    assign q = q_interno;

endmodule

exer7/Estrutural/counterbin_struct_tb.v
`include "counterbin_struct.v"
`timescale 1ns/100ps

module counterbin_struct_tb;


  reg clk_tb;
  reg rst_tb;

  wire [3:0] count_tb;
  
  counterbin_struct uut (
    .clk(clk_tb),
    .rst(rst_tb),
    .q(count_tb)
  );
  
  
  always begin
    #5 clk_tb = ~clk_tb;
  end

 
  initial begin
    $dumpfile("counterbin_struct.vcd");
    $dumpvars(0, counterbin_struct_tb);
    
    
    clk_tb = 0; 
    rst_tb = 1; 
    
    $monitor("Tempo=%0t | clk=%b rst=%b | count[3:0] = %d (%b)",
             $time, clk_tb, rst_tb, count_tb, count_tb);

    #20;

    rst_tb = 0;

    #200;
    
    $finish; 
  end

endmodule

exer7/Estrutural/counterbin_struct.vcd
$date
	Sat Nov 01 16:28:38 2025
$end
$version
	Icarus Verilog
$end
$timescale
	100ps
$end
$scope module counterbin_struct_tb $end
$var wire 4 ! count_tb [3:0] $end
$var reg 1 " clk_tb $end
$var reg 1 # rst_tb $end
$scope module uut $end
$var wire 1 " clk $end
$var wire 4 $ q [3:0] $end
$var wire 1 # rst $end
$var wire 4 % q_interno [3:0] $end
$var wire 4 & d [3:0] $end
$scope module U0_ffd $end
$var wire 1 " clk $end
$var wire 1 ' d $end
$var wire 1 # rst $end
$var reg 1 ( q $end
$upscope $end
$scope module U1_ffd $end
$var wire 1 " clk $end
$var wire 1 ) d $end
$var wire 1 # rst $end
$var reg 1 * q $end
$upscope $end
$scope module U2_ffd $end
$var wire 1 " clk $end
$var wire 1 + d $end
$var wire 1 # rst $end
$var reg 1 , q $end
$upscope $end
$scope module U3_ffd $end
$var wire 1 " clk $end
$var wire 1 - d $end
$var wire 1 # rst $end
$var reg 1 . q $end
$upscope $end
$upscope $end
$upscope $end
$enddefinitions $end
$comment Show the parameter values. $end
$dumpall
$end
#0
$dumpvars
0.
0-
0,
0+
0*
0)
0(
1'
b1 &
b0 %
b0 $
1#
0"
b0 !
$end
#50
1"
#100
0"
#150
1"
#200
0"
0#
#250
0'
1)
b10 &
b1 !
b1 $
b1 %
1(
1"
#300
0"
#350
1'
0(
b11 &
b10 !
b10 $
b10 %
1*
1"
#400
0"
#450
0'
0)
1+
b100 &
b11 !
b11 $
b11 %
1(
1"
#500
0"
#550
1'
0(
0*
b101 &
b100 !
b100 $
b100 %
1,
1"
#600
0"
#650
0'
1)
b110 &
b101 !
b101 $
b101 %
1(
1"
#700
0"
#750
1'
0(
b111 &
b110 !
b110 $
b110 %
1*
1"
#800
0"
#850
0'
0)
0+
1-
b1000 &
b111 !
b111 $
b111 %
1(
1"
#900
0"
#950
1'
0(
0*
0,
b1001 &
b1000 !
b1000 $
b1000 %
1.
1"
#1000
0"
#1050
0'
1)
b1010 &
b1001 !
b1001 $
b1001 %
1(
1"
#1100
0"
#1150
1'
0(
b1011 &
b1010 !
b1010 $
b1010 %
1*
1"
#1200
0"
#1250
0'
0)
1+
b1100 &
b1011 !
b1011 $
b1011 %
1(
1"
#1300
0"
#1350
1'
0(
0*
b1101 &
b1100 !
b1100 $
b1100 %
1,
1"
#1400
0"
#1450
0'
1)
b1110 &
b1101 !
b1101 $
b1101 %
1(
1"
#1500
0"
#1550
1'
0(
b1111 &
b1110 !
b1110 $
b1110 %
1*
1"
#1600
0"
#1650
0'
0)
0+
0-
b0 &
b1111 !
b1111 $
b1111 %
1(
1"
#1700
0"
#1750
1'
0(
0*
0,
b1 &
b0 !
b0 $
b0 %
0.
1"
#1800
0"
#1850
0'
1)
b10 &
b1 !
b1 $
b1 %
1(
1"
#1900
0"
#1950
1'
0(
b11 &
b10 !
b10 $
b10 %
1*
1"
#2000
0"
#2050
0'
0)
1+
b100 &
b11 !
b11 $
b11 %
1(
1"
#2100
0"
#2150
1'
0(
0*
b101 &
b100 !
b100 $
b100 %
1,
1"
