exer7/Comportamental/counterbin_behav.v
module counterbin_behav(
  input clk,      
  input rst,      
  output reg [3:0] count
);

  always @(posedge clk) begin
    
    if (rst) begin
      count <= 4'b0000; 
                      
    end

    else begin
      count <= count + 1;
    end
    
  end

endmodule

exer7/Comportamental/counterbin_behav_tb.v
`include "counterbin_behav.v"
`timescale 1ns/100ps

module counterbin_behav_tb;

  // Sinais que vamos controlar
  reg clk_tb;
  reg rst_tb;
  
  // Sinal que vamos observar
  wire [3:0] count_tb;
  
  // Instanciação do Contador
  counterbin_behav uut (
    .clk(clk_tb),
    .rst(rst_tb),
    .count(count_tb)
  );
  
  // 1. Geração de Clock
  // Este bloco 'always' roda para sempre,
  // invertendo o clk_tb a cada 5ns.
  // Isso cria um clock com período de 10ns (5ns LOW, 5ns HIGH).
  always begin
    #5 clk_tb = ~clk_tb;
  end

  // 2. Bloco de Estímulos e Simulação
  initial begin
    $dumpfile("counterbin_behav.vcd");
    $dumpvars(0, counterbin_behav_tb);
    
    // Inicializa os sinais
    clk_tb = 0; // Começa o clock em 0
    rst_tb = 1; // Começa com o reset ATIVADO
    
    // Monitora os sinais. %d mostra o valor em decimal (útil!)
    $monitor("Tempo=%0t | clk=%b rst=%b | count[3:0] = %d (%b)",
             $time, clk_tb, rst_tb, count_tb, count_tb);
             
    // 1. Mantém o reset por 20ns (2 ciclos de clock)
    #20;
    
    // 2. Desliga o reset. Agora o contador deve começar a contar.
    rst_tb = 0;
    
    // 3. Deixa a simulação rodar por 200ns (20 ciclos de clock)
    // Isso é suficiente para ver o contador ir de 0 a 15 e "virar" (overflow)
    #200;
    
    $finish; // Termina a simulação
  end

endmodule

exer7/Comportamental/counterbin_behav.vcd
$date
	Sat Nov 01 16:03:59 2025
$end
$version
	Icarus Verilog
$end
$timescale
	100ps
$end
$scope module counterbin_behav_tb $end
$var wire 4 ! count_tb [3:0] $end
$var reg 1 " clk_tb $end
$var reg 1 # rst_tb $end
$scope module uut $end
$var wire 1 " clk $end
$var wire 1 # rst $end
$var reg 4 $ count [3:0] $end
$upscope $end
$upscope $end
$enddefinitions $end
$comment Show the parameter values. $end
$dumpall
$end
#0
$dumpvars
bx $
1#
0"
bx !
$end
#50
b0 !
b0 $
1"
#100
0"
#150
1"
#200
0"
0#
#250
b1 !
b1 $
1"
#300
0"
#350
b10 !
b10 $
1"
#400
0"
#450
b11 !
b11 $
1"
#500
0"
#550
b100 !
b100 $
1"
#600
0"
#650
b101 !
b101 $
1"
#700
0"
#750
b110 !
b110 $
1"
#800
0"
#850
b111 !
b111 $
1"
#900
0"
#950
b1000 !
b1000 $
1"
#1000
0"
#1050
b1001 !
b1001 $
1"
#1100
0"
#1150
b1010 !
b1010 $
1"
#1200
0"
#1250
b1011 !
b1011 $
1"
#1300
0"
#1350
b1100 !
b1100 $
1"
#1400
0"
#1450
b1101 !
b1101 $
1"
#1500
0"
#1550
b1110 !
b1110 $
1"
#1600
0"
#1650
b1111 !
b1111 $
1"
#1700
0"
#1750
b0 !
b0 $
1"
#1800
0"
#1850
b1 !
b1 $
1"
#1900
0"
#1950
b10 !
b10 $
1"
#2000
0"
#2050
b11 !
b11 $
1"
#2100
0"
#2150
b100 !
b100 $
1"
