exer8/Comportamental/fullsubtractor_behav.v
module fullsubtractor_behav(
    input wire a,
    input wire b,
    input wire borrow_in,
    output wire diff,
    output wire borrow_out
);

    assign diff = a ^ b ^ borrow_in;

    assign borrow_out = (~a & b) | (~a & borrow_in) | (b & borrow_in);

endmodule

exer8/Comportamental/fullsubtractor_behav_tb.v
`include "fullsubtractor_behav.v"
`timescale 1ns/100ps

module fullsubtractor_behav_tb;


    reg a_tb, b_tb, bin_tb;

    wire diff_tb, bout_tb;

    fullsubtractor_behav uut (
        .a(a_tb),
        .b(b_tb),
        .borrow_in(bin_tb),
        .diff(diff_tb),
        .borrow_out(bout_tb)
    );


    initial begin
        $dumpfile("fullsubtractor_behav.vcd");
        $dumpvars(0, fullsubtractor_behav_tb);

        $monitor("Tempo=%0t | a=%b b=%b bin=%b | bout=%b diff=%b",
                 $time, a_tb, b_tb, bin_tb, bout_tb, diff_tb);

        a_tb=0; b_tb=0; bin_tb=0; #10; // 0-0-0 = 0 (bout=0, diff=0)
        a_tb=0; b_tb=0; bin_tb=1; #10; // 0-0-1 = -1 (bout=1, diff=1)
        a_tb=0; b_tb=1; bin_tb=0; #10; // 0-1-0 = -1 (bout=1, diff=1)
        a_tb=0; b_tb=1; bin_tb=1; #10; // 0-1-1 = -2 (bout=1, diff=0)
        a_tb=1; b_tb=0; bin_tb=0; #10; // 1-0-0 = 1 (bout=0, diff=1)
        a_tb=1; b_tb=0; bin_tb=1; #10; // 1-0-1 = 0 (bout=0, diff=0)
        a_tb=1; b_tb=1; bin_tb=0; #10; // 1-1-0 = 0 (bout=0, diff=0)
        a_tb=1; b_tb=1; bin_tb=1; #10; // 1-1-1 = -1 (bout=1, diff=1)
        
        $finish;
    end

endmodule

exer8/Comportamental/fullsubtractor_behav.vcd
$date
	Sat Nov 01 16:39:39 2025
$end
$version
	Icarus Verilog
$end
$timescale
	100ps
$end
$scope module fullsubtractor_behav_tb $end
$var wire 1 ! diff_tb $end
$var wire 1 " bout_tb $end
$var reg 1 # a_tb $end
$var reg 1 $ b_tb $end
$var reg 1 % bin_tb $end
$scope module uut $end
$var wire 1 # a $end
$var wire 1 $ b $end
$var wire 1 % borrow_in $end
$var wire 1 " borrow_out $end
$var wire 1 ! diff $end
$upscope $end
$upscope $end
$enddefinitions $end
$comment Show the parameter values. $end
$dumpall
$end
#0
$dumpvars
0%
0$
0#
0"
0!
$end
#100
1"
1!
1%
#200
0%
1$
#300
0!
1%
#400
0"
1!
0%
0$
1#
#500
0!
1%
#600
0%
1$
#700
1"
1!
1%
